Workbook

Sheet How to use
A1: How to use this workbook
A2: 1. Assumptions tab: replace the yellow cells with your real freelancer and album-printer quotes first.
A3: 2. Package Costing tab: edit price (column C) or quantities. Status turns green (OK ≥30%), yellow (Thin 20–30%) or red (Reprice <20%).
A4: 3. Revenue Scenario tab: enter expected bookings per month to see revenue, contribution and advance cash.
A6: Colour legend
A7: Blue text = input you can change · Black = formula · Green = linked from another tab · Yellow fill = key assumption to verify
A9: Where the numbers come from
A10: From you: crew ₹5K–8K/day, album ₹3K–6K, 25 km free radius, 30/50/20 payment, 1-week previews, 45-day delivery.
A11: Estimates (verify): editing, drone, LED wall, live streaming, conveyance, short-session factor, vehicle cost per km.
A12: Direct cost excludes your own time, equipment, marketing and GST.
A14: Key findings
A15: • Wedding Essential (₹49,999) is the thinnest package (~22%). It is your entry offer: shoot one role yourself, or raise to ₹54,999.
... A18: • Add-ons (drone, albums, reels, express delivery) are 30–70% margin. Train yourself to offer them on every booking call.

Sheet Assumptions
A1: McreatiK Studios – Cost Assumptions (Chennai base)
A2: Blue = input you can edit. Yellow = key assumptions to confirm with your actual vendor quotes.
A4: Cost driver | B4: Unit | C4: Rate (₹) | D4: Source / note
A5: Traditional photographer | B5: per full session (≤6 hrs) | C5: 5500 | D5: User range ₹5K–8K/day; traditional shooters at the lower end
A6: Traditional videographer | B6: per full session | C6: 5500 | D6: User range ₹5K–8K/day
A7: Candid photographer | B7: per full session | C7: 7500 | D7: User range ₹5K–8K/day; candid at the upper end
A8: Cinematographer | B8: per full session | C8: 7500 | D8: User range ₹5K–8K/day
A9: Short-session crew (candid/cine) | B9: per session ≤3 hrs | C9: =C7*$C$30 -> 4500 | D9: Candid rate × short-session factor (below)
A10: Drone operator + drone | B10: per session | C10: 5500 | D10: Estimate – confirm with local operator
A11: Photo editing – traditional | B11: per session | C11: 1500 | D11: Estimate (outsourced culling + colour)
A12: Photo editing – candid | B12: per session | C12: 1500 | D12: Estimate (outsourced culling + colour)
A13: Traditional video editing | B13: per session | C13: 2000 | D13: Estimate
A14: Highlight video (3–4 min) | B14: per film | C14: 2000 | D14: Estimate
A15: Cinematic film + teaser | B15: per film (5–7 min) | C15: 8000 | D15: Estimate; qty 1.25 = longer 8–10 min film
A16: Instagram reel edit | B16: per reel | C16: 1000 | D16: Estimate
A17: Album 12x36, 30 sheets | B17: per album | C17: 4000 | D17: User range ₹3K–6K
A18: Album 12x36, 40 sheets | B18: per album | C18: 5000 | D18: User range ₹3K–6K
A19: Album 12x36, 50 sheets premium | B19: per album | C19: 6000 | D19: Top of user range ₹3K–6K
A20: Album 12x30, 25 sheets (parents) | B20: per album | C20: 3500 | D20: User range ₹3K–6K
A21: Compact album 12x18, 20 sheets | B21: per album | C21: 2500 | D21: Estimate
... A26: Other direct cost (₹ amount) | B26: ₹1 per unit | C26: 1 | D26: Qty column holds the rupee amount (vendor quotes, extra sheets, props)
A29: Other settings
A30: Short-session factor | B30: × full-session rate | C30: 0.6 | D30: Assumes freelancers accept ~60% of day rate for ≤3 hr jobs – confirm
A31: Target contribution margin | C31: 0.3 | D31: Below this the package is flagged 'Thin'
A32: Reprice threshold | C32: 0.2 | D32: Below this the package is flagged 'Reprice'
A33: Travel charge to client (beyond 25 km) | B33: ₹ per km, round trip | C33: 20 | D33: Client-facing rate
A34: Vehicle cost to you | B34: ₹ per km | C34: 14 | D34: Estimate – cab/fuel cost
A35: Free travel radius | B35: km from Chennai base | C35: 25 | D35: From user
A36: Booking advance | B36: % of package | C36: 0.3 | D36: From user: 30 / 50 / 20
A37: Event-day payment | B37: % of package | C37: 0.5 | D37: From user
A38: Before final delivery | B38: % of package | C38: 0.2 | D38: From user
A39: Margin per km on travel | C39: =C33-C34 -> 6
A41: Contribution margin = package price − direct delivery cost. It does NOT include your time, equipment depreciation, marketing, software or GST. Aim for 30%+ so there is room for those.

Sheet Package Costing
A1: McreatiK Studios – Package Costing & Margins
A2: Quantities (blue) × unit rates (row 4, linked from Assumptions) = direct cost. Edit price or quantities; margin and status update.
A4: Unit rate → | D4: =Assumptions!$C$5 -> 5500 | E4: =Assumptions!$C$6 -> 5500 | F4: =Assumptions!$C$7 -> 7500 | G4: =Assumptions!$C$8 -> 7500 | H4: =Assumptions!$C$9 -> 4500 | I4: =Assumptions!$C$10 -> 5500 | J4: =Assumptions!$C$11 -> 1500 | K4: =Assumptions!$C$12 -> 1500 | L4: =Assumptions!$C$13 -> 2000 | M4: =Assumptions!$C$14 -> 2000 | N4: =Assumptions!$C$15 -> 8000 | O4: =Assumptions!$C$16 -> 1000 | P4: =Assumptions!$C$17 -> 4000 | Q4: =Assumptions!$C$18 -> 5000 | R4: =Assumptions!$C$19 -> 6000 | S4: =Assumptions!$C$20 -> 3500 | T4: =Assumptions!$C$21 -> 2500 | U4: =Assumptions!$C$22 -> 1000 | V4: =Assumptions!$C$23 -> 1000 | W4: =Assumptions!$C$24 -> 800 | X4: =Assumptions!$C$25 -> 500 | Y4: =Assumptions!$C$26 -> 1
A5: Category | B5: Package / add-on | C5: Price (₹) | D5: Traditional photographer | E5: Traditional videographer | F5: Candid photographer | G5: Cinematographer | H5: Short-session crew (candid/cine) | I5: Drone operator + drone | J5: Photo editing – traditional | K5: Photo editing – candid | L5: Traditional video editing | M5: Highlight video (3–4 min) | N5: Cinematic film + teaser | O5: Instagram reel edit | P5: Album 12x36, 30 sheets | Q5: Album 12x36, 40 sheets | R5: Album 12x36, 50 sheets premium | S5: Album 12x30, 25 sheets (parents) | T5: Compact album 12x18, 20 sheets | U5: Mini album / photobook 8x12 | V5: Album design | W5: Pen drive + box + online gallery | X5: Crew local conveyance | Y5: Other direct cost (₹ amount) | Z5: Direct cost (₹) | AA5: Contribution (₹) | AB5: Margin % | AC5: Status | AD5: What's included / notes
A6: Wedding | B6: Essential | C6: 49999 | D6: 2 | E6: 2 | J6: 2 | L6: 2 | M6: 1 | P6: 1 | V6: 1 | W6: 1 | X6: 4 | Z6: =SUMPRODUCT($D$4:$Y$4,D6:Y6) -> 38800 | AA6: =C6-Z6 -> 11199 | AB6: =IFERROR(AA6/C6,0) -> 0.22398448 | AC6: =IF(AB6>=Assumptions!$C$31,"OK",IF(AB6>=Assumptions!$C$32,"Thin","Reprice")) -> Thin | AD6: Reception + Muhurtham. Trad photo + trad video. 30-sheet album. Thin margin – shoot one role yourself to lift it.
A7: Wedding | B7: Classic | C7: 84999 | D7: 2 | E7: 2 | F7: 2 | J7: 2 | K7: 2 | L7: 2 | M7: 1 | Q7: 1 | V7: 1 | W7: 1 | X7: 6 | Z7: =SUMPRODUCT($D$4:$Y$4,D7:Y7) -> 58800 | AA7: =C7-Z7 -> 26199 | AB7: =IFERROR(AA7/C7,0) -> 0.30822716 | AC7: =IF(AB7>=Assumptions!$C$31,"OK",IF(AB7>=Assumptions!$C$32,"Thin","Reprice")) -> OK | AD7: Adds candid photographer. 40-sheet album.
A8: Wedding | B8: Signature | C8: 124999 | D8: 2 | E8: 2 | F8: 2 | G8: 2 | J8: 2 | K8: 2 | L8: 2 | N8: 1 | O8: 2 | Q8: 1 | U8: 2 | V8: 3 | W8: 1 | X8: 8 | Z8: =SUMPRODUCT($D$4:$Y$4,D8:Y8) -> 86800 | AA8: =C8-Z8 -> 38199 | AB8: =IFERROR(AA8/C8,0) -> 0.30559444 | AC8: =IF(AB8>=Assumptions!$C$31,"OK",IF(AB8>=Assumptions!$C$32,"Thin","Reprice")) -> OK | AD8: Full 4-person crew, cinematic film + teaser, 2 reels, 2 mini albums.
A9: Wedding | B9: Grand | C9: 149999 | D9: 2 | E9: 2 | F9: 2 | G9: 2 | H9: 2 | I9: 1 | J9: 2 | K9: 3 | L9: 2 | N9: 1.25 | O9: 3 | R9: 1 | S9: 1 | V9: 2 | W9: 1 | X9: 11 | Z9: =SUMPRODUCT($D$4:$Y$4,D9:Y9) -> 108800 | AA9: =C9-Z9 -> 41199 | AB9: =IFERROR(AA9/C9,0) -> 0.27466183 | AC9: =IF(AB9>=Assumptions!$C$31,"OK",IF(AB9>=Assumptions!$C$32,"Thin","Reprice")) -> Thin | AD9: Signature + short ceremony session (Nalangu/Mehendi/Haldi) + drone at 1 session + parents' album.
A10: Wedding add-on | B10: Extra ceremony session – Essential crew | C10: 23499 | D10: 1 | E10: 1 | J10: 1 | L10: 1 | X10: 2 | Y10: 600 | Z10: =SUMPRODUCT($D$4:$Y$4,D10:Y10) -> 16100 | AA10: =C10-Z10 -> 7399 | AB10: =IFERROR(AA10/C10,0) -> 0.31486446 | AC10: =IF(AB10>=Assumptions!$C$31,"OK",IF(AB10>=Assumptions!$C$32,"Thin","Reprice")) -> OK | AD10: Engagement / Nalangu / Sangeet added to a wedding booking. OT = extra album sheets.
A11: Wedding add-on | B11: Extra ceremony session – Classic crew | C11: 36999 | D11: 1 | E11: 1 | F11: 1 | J11: 1 | K11: 1 | L11: 1 | X11: 3 | Y11: 600 | Z11: =SUMPRODUCT($D$4:$Y$4,D11:Y11) -> 25600 | AA11: =C11-Z11 -> 11399 | AB11: =IFERROR(AA11/C11,0) -> 0.30808941 | AC11: =IF(AB11>=Assumptions!$C$31,"OK",IF(AB11>=Assumptions!$C$32,"Thin","Reprice")) -> OK
A12: Wedding add-on | B12: Extra ceremony session – Signature crew | C12: 51999 | D12: 1 | E12: 1 | F12: 1 | G12: 1 | J12: 1 | K12: 1 | L12: 1 | N12: 0.25 | X12: 4 | Y12: 600 | Z12: =SUMPRODUCT($D$4:$Y$4,D12:Y12) -> 35600 | AA12: =C12-Z12 -> 16399 | AB12: =IFERROR(AA12/C12,0) -> 0.31537145 | AC12: =IF(AB12>=Assumptions!$C$31,"OK",IF(AB12>=Assumptions!$C$32,"Thin","Reprice")) -> OK
A13: Pre-wedding | B13: Pre-wedding shoot | C13: 34999 | F13: 1 | G13: 1 | K13: 1 | N13: 0.625 | X13: 2 | Y13: 500 | Z13: =SUMPRODUCT($D$4:$Y$4,D13:Y13) -> 23000 | AA13: =C13-Z13 -> 11999 | AB13: =IFERROR(AA13/C13,0) -> 0.34283837 | AC13: =IF(AB13>=Assumptions!$C$31,"OK",IF(AB13>=Assumptions!$C$32,"Thin","Reprice")) -> OK | AD13: Up to 5 hrs, 2 outfits, Chennai location. Location/permit fees extra.
A14: Ceremony | B14: Photo Only | C14: 16999 | D14: 1 | J14: 1 | T14: 1 | V14: 1 | W14: 1 | X14: 1 | Z14: =SUMPRODUCT($D$4:$Y$4,D14:Y14) -> 11800 | AA14: =C14-Z14 -> 5199 | AB14: =IFERROR(AA14/C14,0) -> 0.30584152 | AC14: =IF(AB14>=Assumptions!$C$31,"OK",IF(AB14>=Assumptions!$C$32,"Thin","Reprice")) -> OK | AD14: Engagement, puberty function, valaikaappu, naming, ear-piercing, housewarming, 60th/80th. 1 session ≤6 hrs.
A15: Ceremony | B15: Essential | C15: 31999 | D15: 1 | E15: 1 | J15: 1 | L15: 1 | M15: 1 | T15: 1 | V15: 1 | W15: 1 | X15: 2 | Z15: =SUMPRODUCT($D$4:$Y$4,D15:Y15) -> 21800 | AA15: =C15-Z15 -> 10199 | AB15: =IFERROR(AA15/C15,0) -> 0.31872871 | AC15: =IF(AB15>=Assumptions!$C$31,"OK",IF(AB15>=Assumptions!$C$32,"Thin","Reprice")) -> OK | AD15: Trad photo + trad video.
A16: Ceremony | B16: Premium | C16: 47999 | D16: 1 | E16: 1 | F16: 1 | J16: 1 | K16: 1 | L16: 1 | M16: 1 | O16: 1 | S16: 1 | V16: 1 | W16: 1 | X16: 3 | Z16: =SUMPRODUCT($D$4:$Y$4,D16:Y16) -> 33300 | AA16: =C16-Z16 -> 14699 | AB16: =IFERROR(AA16/C16,0) -> 0.30623555 | AC16: =IF(AB16>=Assumptions!$C$31,"OK",IF(AB16>=Assumptions!$C$32,"Thin","Reprice")) -> OK | AD16: Adds candid + reel + 12x30 album.
A17: Birthday | B17: Birthday Photo | C17: 12999 | H17: 1 | K17: 1 | U17: 1 | W17: 0.5 | X17: 1 | Z17: =SUMPRODUCT($D$4:$Y$4,D17:Y17) -> 7900 | AA17: =C17-Z17 -> 5099 | AB17: =IFERROR(AA17/C17,0) -> 0.39226094 | AC17: =IF(AB17>=Assumptions!$C$31,"OK",IF(AB17>=Assumptions!$C$32,"Thin","Reprice")) -> OK | AD17: ≤3 hrs, candid photos + 8x12 photobook.
A18: Birthday | B18: Birthday Photo + Video | C18: 24999 | H18: 2 | K18: 1 | M18: 1 | O18: 1 | U18: 1 | W18: 0.5 | X18: 2 | Z18: =SUMPRODUCT($D$4:$Y$4,D18:Y18) -> 15900 | AA18: =C18-Z18 -> 9099 | AB18: =IFERROR(AA18/C18,0) -> 0.36397456 | AC18: =IF(AB18>=Assumptions!$C$31,"OK",IF(AB18>=Assumptions!$C$32,"Thin","Reprice")) -> OK | AD18: ≤3 hrs, candid + cinematic highlight + reel.
A19: Corporate | B19: Corporate Half Day – Photo | C19: 14999 | H19: 1 | K19: 1 | W19: 0.5 | X19: 1 | Z19: =SUMPRODUCT($D$4:$Y$4,D19:Y19) -> 6900 | AA19: =C19-Z19 -> 8099 | AB19: =IFERROR(AA19/C19,0) -> 0.53996933 | AC19: =IF(AB19>=Assumptions!$C$31,"OK",IF(AB19>=Assumptions!$C$32,"Thin","Reprice")) -> OK | AD19: ≤4 hrs. 30 edited picks in 24 hrs.
A20: Corporate | B20: Corporate Full Day – Photo | C20: 24999 | F20: 1 | K20: 2 | W20: 0.5 | X20: 1 | Z20: =SUMPRODUCT($D$4:$Y$4,D20:Y20) -> 11400 | AA20: =C20-Z20 -> 13599 | AB20: =IFERROR(AA20/C20,0) -> 0.54398176 | AC20: =IF(AB20>=Assumptions!$C$31,"OK",IF(AB20>=Assumptions!$C$32,"Thin","Reprice")) -> OK | AD20: ≤8 hrs.
A21: Corporate | B21: Corporate Full Day – Photo + Video | C21: 49999 | F21: 1 | G21: 1 | K21: 2 | M21: 1 | O21: 2 | W21: 1 | X21: 2 | Y21: 4000 | Z21: =SUMPRODUCT($D$4:$Y$4,D21:Y21) -> 27800 | AA21: =C21-Z21 -> 22199 | AB21: =IFERROR(AA21/C21,0) -> 0.44398888 | AC21: =IF(AB21>=Assumptions!$C$31,"OK",IF(AB21>=Assumptions!$C$32,"Thin","Reprice")) -> OK | AD21: Recap film, 2 reels, speech clips (OT).
A22: Add-on | B22: Drone coverage (per session) | C22: 9999 | I22: 1 | X22: 1 | Z22: =SUMPRODUCT($D$4:$Y$4,D22:Y22) -> 6000 | AA22: =C22-Z22 -> 3999 | AB22: =IFERROR(AA22/C22,0) -> 0.39993999 | AC22: =IF(AB22>=Assumptions!$C$31,"OK",IF(AB22>=Assumptions!$C$32,"Thin","Reprice")) -> OK | AD22: Subject to venue permission and DGCA airspace rules.
A23: Add-on | B23: Extra candid photographer (per session) | C23: 13999 | F23: 1 | K23: 1 | X23: 1 | Z23: =SUMPRODUCT($D$4:$Y$4,D23:Y23) -> 9500 | AA23: =C23-Z23 -> 4499 | AB23: =IFERROR(AA23/C23,0) -> 0.3213801 | AC23: =IF(AB23>=Assumptions!$C$31,"OK",IF(AB23>=Assumptions!$C$32,"Thin","Reprice")) -> OK
A24: Add-on | B24: Extra cinematographer (per session) | C24: 14999 | G24: 1 | X24: 1 | Y24: 2000 | Z24: =SUMPRODUCT($D$4:$Y$4,D24:Y24) -> 10000 | AA24: =C24-Z24 -> 4999 | AB24: =IFERROR(AA24/C24,0) -> 0.33328889 | AC24: =IF(AB24>=Assumptions!$C$31,"OK",IF(AB24>=Assumptions!$C$32,"Thin","Reprice")) -> OK | AD24: OT = extra edit time.
A25: Add-on | B25: Live streaming (per session) | C25: 14999 | X25: 1 | Y25: 8000 | Z25: =SUMPRODUCT($D$4:$Y$4,D25:Y25) -> 8500 | AA25: =C25-Z25 -> 6499 | AB25: =IFERROR(AA25/C25,0) -> 0.43329555 | AC25: =IF(AB25>=Assumptions!$C$31,"OK",IF(AB25>=Assumptions!$C$32,"Thin","Reprice")) -> OK | AD25: Estimate – streaming kit + data + operator.
A26: Add-on | B26: LED wall live display (per session) | C26: 20999 | Y26: 14000 | Z26: =SUMPRODUCT($D$4:$Y$4,D26:Y26) -> 14000 | AA26: =C26-Z26 -> 6999 | AB26: =IFERROR(AA26/C26,0) -> 0.33330159 | AC26: =IF(AB26>=Assumptions!$C$31,"OK",IF(AB26>=Assumptions!$C$32,"Thin","Reprice")) -> OK | AD26: Estimate – 8x12 ft vendor rental. Get 2 quotes.
A27: Add-on | B27: Same-day highlight video | C27: 19999 | Y27: 9000 | Z27: =SUMPRODUCT($D$4:$Y$4,D27:Y27) -> 9000 | AA27: =C27-Z27 -> 10999 | AB27: =IFERROR(AA27/C27,0) -> 0.5499775 | AC27: =IF(AB27>=Assumptions!$C$31,"OK",IF(AB27>=Assumptions!$C$32,"Thin","Reprice")) -> OK | AD27: On-site editor + setup.
A28: Add-on | B28: Extra album 12x30, 25 sheets | C28: 6999 | S28: 1 | V28: 1 | Z28: =SUMPRODUCT($D$4:$Y$4,D28:Y28) -> 4500 | AA28: =C28-Z28 -> 2499 | AB28: =IFERROR(AA28/C28,0) -> 0.35705101 | AC28: =IF(AB28>=Assumptions!$C$31,"OK",IF(AB28>=Assumptions!$C$32,"Thin","Reprice")) -> OK
A29: Add-on | B29: Premium lay-flat album upgrade | C29: 5999 | Y29: 3000 | Z29: =SUMPRODUCT($D$4:$Y$4,D29:Y29) -> 3000 | AA29: =C29-Z29 -> 2999 | AB29: =IFERROR(AA29/C29,0) -> 0.49991665 | AC29: =IF(AB29>=Assumptions!$C$31,"OK",IF(AB29>=Assumptions!$C$32,"Thin","Reprice")) -> OK
A30: Add-on | B30: Mini album 8x12 | C30: 2499 | U30: 1 | Y30: 300 | Z30: =SUMPRODUCT($D$4:$Y$4,D30:Y30) -> 1300 | AA30: =C30-Z30 -> 1199 | AB30: =IFERROR(AA30/C30,0) -> 0.47979192 | AC30: =IF(AB30>=Assumptions!$C$31,"OK",IF(AB30>=Assumptions!$C$32,"Thin","Reprice")) -> OK
A31: Add-on | B31: Framed print 20x30 | C31: 3499 | Y31: 1500 | Z31: =SUMPRODUCT($D$4:$Y$4,D31:Y31) -> 1500 | AA31: =C31-Z31 -> 1999 | AB31: =IFERROR(AA31/C31,0) -> 0.57130609 | AC31: =IF(AB31>=Assumptions!$C$31,"OK",IF(AB31>=Assumptions!$C$32,"Thin","Reprice")) -> OK
A32: Add-on | B32: Reels pack (3 reels) | C32: 5999 | O32: 3 | Z32: =SUMPRODUCT($D$4:$Y$4,D32:Y32) -> 3000 | AA32: =C32-Z32 -> 2999 | AB32: =IFERROR(AA32/C32,0) -> 0.49991665 | AC32: =IF(AB32>=Assumptions!$C$31,"OK",IF(AB32>=Assumptions!$C$32,"Thin","Reprice")) -> OK
A33: Add-on | B33: Digital video invitation | C33: 4999 | Y33: 1500 | Z33: =SUMPRODUCT($D$4:$Y$4,D33:Y33) -> 1500 | AA33: =C33-Z33 -> 3499 | AB33: =IFERROR(AA33/C33,0) -> 0.69993999 | AC33: =IF(AB33>=Assumptions!$C$31,"OK",IF(AB33>=Assumptions!$C$32,"Thin","Reprice")) -> OK | AD33: Cross-sell from McreatiK Studios digital invites.
A34: Add-on | B34: Express delivery (21 days) | C34: 9999 | Y34: 4000 | Z34: =SUMPRODUCT($D$4:$Y$4,D34:Y34) -> 4000 | AA34: =C34-Z34 -> 5999 | AB34: =IFERROR(AA34/C34,0) -> 0.59996 | AC34: =IF(AB34>=Assumptions!$C$31,"OK",IF(AB34>=Assumptions!$C$32,"Thin","Reprice")) -> OK | AD34: Rush editing premium.
A35: Add-on | B35: Raw video footage on drive | C35: 2999 | Y35: 1500 | Z35: =SUMPRODUCT($D$4:$Y$4,D35:Y35) -> 1500 | AA35: =C35-Z35 -> 1499 | AB35: =IFERROR(AA35/C35,0) -> 0.49983328 | AC35: =IF(AB35>=Assumptions!$C$31,"OK",IF(AB35>=Assumptions!$C$32,"Thin","Reprice")) -> OK
A36: Add-on | B36: Extra hour (per crew member) | C36: 2000 | Y36: 1000 | Z36: =SUMPRODUCT($D$4:$Y$4,D36:Y36) -> 1000 | AA36: =C36-Z36 -> 1000 | AB36: =IFERROR(AA36/C36,0) -> 0.5 | AC36: =IF(AB36>=Assumptions!$C$31,"OK",IF(AB36>=Assumptions!$C$32,"Thin","Reprice")) -> OK
B38: OT column = rupee amount of any extra direct cost (rate ₹1). Fractional quantities = partial use (e.g. 0.5 gallery).

Sheet Revenue Scenario
A1: Monthly Revenue Scenario
A2: EXAMPLE numbers for a peak-season month – replace bookings (blue) with your real pipeline. Not a forecast.
A4: Category | B4: Package | C4: Price (₹) | D4: Contribution / unit (₹) | E4: Bookings | F4: Revenue (₹) | G4: Contribution (₹)
A5: ='Package Costing'!A6 -> Wedding | B5: ='Package Costing'!B6 -> Essential | C5: ='Package Costing'!C6 -> 49999 | D5: ='Package Costing'!AA6 -> 11199 | E5: 1 | F5: =C5*E5 -> 49999 | G5: =D5*E5 -> 11199
A6: ='Package Costing'!A7 -> Wedding | B6: ='Package Costing'!B7 -> Classic | C6: ='Package Costing'!C7 -> 84999 | D6: ='Package Costing'!AA7 -> 26199 | E6: 2 | F6: =C6*E6 -> 169998 | G6: =D6*E6 -> 52398
A7: ='Package Costing'!A8 -> Wedding | B7: ='Package Costing'!B8 -> Signature | C7: ='Package Costing'!C8 -> 124999 | D7: ='Package Costing'!AA8 -> 38199 | E7: 1 | F7: =C7*E7 -> 124999 | G7: =D7*E7 -> 38199
A8: ='Package Costing'!A9 -> Wedding | B8: ='Package Costing'!B9 -> Grand | C8: ='Package Costing'!C9 -> 149999 | D8: ='Package Costing'!AA9 -> 41199 | E8: 0 | F8: =C8*E8 -> 0 | G8: =D8*E8 -> 0
A9: ='Package Costing'!A10 -> Wedding add-on | B9: ='Package Costing'!B10 -> Extra ceremony session – Essential crew | C9: ='Package Costing'!C10 -> 23499 | D9: ='Package Costing'!AA10 -> 7399 | E9: 0 | F9: =C9*E9 -> 0 | G9: =D9*E9 -> 0
A10: ='Package Costing'!A11 -> Wedding add-on | B10: ='Package Costing'!B11 -> Extra ceremony session – Classic crew | C10: ='Package Costing'!C11 -> 36999 | D10: ='Package Costing'!AA11 -> 11399 | E10: 0 | F10: =C10*E10 -> 0 | G10: =D10*E10 -> 0
A11: ='Package Costing'!A12 -> Wedding add-on | B11: ='Package Costing'!B12 -> Extra ceremony session – Signature crew | C11: ='Package Costing'!C12 -> 51999 | D11: ='Package Costing'!AA12 -> 16399 | E11: 0 | F11: =C11*E11 -> 0 | G11: =D11*E11 -> 0
A12: ='Package Costing'!A13 -> Pre-wedding | B12: ='Package Costing'!B13 -> Pre-wedding shoot | C12: ='Package Costing'!C13 -> 34999 | D12: ='Package Costing'!AA13 -> 11999 | E12: 0 | F12: =C12*E12 -> 0 | G12: =D12*E12 -> 0
A13: ='Package Costing'!A14 -> Ceremony | B13: ='Package Costing'!B14 -> Photo Only | C13: ='Package Costing'!C14 -> 16999 | D13: ='Package Costing'!AA14 -> 5199 | E13: 0 | F13: =C13*E13 -> 0 | G13: =D13*E13 -> 0
A14: ='Package Costing'!A15 -> Ceremony | B14: ='Package Costing'!B15 -> Essential | C14: ='Package Costing'!C15 -> 31999 | D14: ='Package Costing'!AA15 -> 10199 | E14: 2 | F14: =C14*E14 -> 63998 | G14: =D14*E14 -> 20398
A15: ='Package Costing'!A16 -> Ceremony | B15: ='Package Costing'!B16 -> Premium | C15: ='Package Costing'!C16 -> 47999 | D15: ='Package Costing'!AA16 -> 14699 | E15: 1 | F15: =C15*E15 -> 47999 | G15: =D15*E15 -> 14699
A16: ='Package Costing'!A17 -> Birthday | B16: ='Package Costing'!B17 -> Birthday Photo | C16: ='Package Costing'!C17 -> 12999 | D16: ='Package Costing'!AA17 -> 5099 | E16: 0 | F16: =C16*E16 -> 0 | G16: =D16*E16 -> 0
... A35: ='Package Costing'!A36 -> Add-on | B35: ='Package Costing'!B36 -> Extra hour (per crew member) | C35: ='Package Costing'!C36 -> 2000 | D35: ='Package Costing'!AA36 -> 1000 | E35: 0 | F35: =C35*E35 -> 0 | G35: =D35*E35 -> 0
B36: Total | E36: =SUM(E5:E35) -> 11 | F36: =SUM(F5:F35) -> 505989 | G36: =SUM(G5:G35) -> 159489
B37: Blended margin | G37: =IFERROR(G36/F36,0) -> 0.3152025
B38: Cash collected as booking advances (30%) | F38: =F36*Assumptions!C36 -> 151796.7
B40: Reality check: 4 weddings + 4 ceremonies in one month means ~16 shoot sessions and ~45 days of editing load. Off-season months (Aadi, Margazhi) will be far lower.
